Metadata-Version: 1.1
Name: kong-hmac
Version: 1.0.0
Summary: Kong 网关HMAC鉴权SDK
Home-page: https://git.woa.com/nops/ngate/ngate-sdk/ngate-python.git
Author: Jager
Author-email: im@zhang.ge
License: Apache 2.0
Platform: UNKNOWN
Classifier: Programming Language :: Python :: 3
